onnxdecoder/__init__.py
onnxdecoder/main.py
onnxdecoder/version.py
onnxdecoder-0.0.2.dist-info/METADATA
onnxdecoder-0.0.2.dist-info/WHEEL
onnxdecoder-0.0.2.dist-info/top_level.txt
onnxdecoder-0.0.2.dist-info/RECORD
