Metadata-Version: 2.1
Name: onnxdecoder
Version: 0.0.2
Summary: ONNXDecoder Python SDK
Home-page: https://zhenghaotan.com
Author: Zheng Hao Tan
Author-email: hi@zhenghaotan.com
Project-URL: Source Code, https://github.com/tzhenghao/onnxdecoder
Keywords: artificial intelligence,machine learning,pytorch,tensorflow,onnx,development,debugging,benchmarking
Classifier: Development Status :: 3 - Alpha
Classifier: Intended Audience :: Developers
Classifier: Intended Audience :: Science/Research
Classifier: Topic :: Scientific/Engineering :: Artificial Intelligence
Classifier: Topic :: Software Development :: Build Tools
Classifier: Topic :: Software Development :: Compilers
Classifier: Topic :: Software Development :: Debuggers
Classifier: License :: OSI Approved :: Apache Software License
Classifier: Programming Language :: Python :: 3
Classifier: Programming Language :: Python :: 3.7
Classifier: Programming Language :: Python :: 3.8
Classifier: Programming Language :: Python :: 3.9
Classifier: Programming Language :: Python :: 3.10
Classifier: Programming Language :: Python :: 3 :: Only
Requires-Python: >=3.7, <4
Requires-Dist: black (==23.1.0)
Requires-Dist: click (==8.1.3)
Requires-Dist: colorama (==0.4.6)
Requires-Dist: flake8 (==6.0.0)
Requires-Dist: isort (==5.12.0)
Requires-Dist: mypy (==0.950)
Requires-Dist: numpy (==1.23.0)
Requires-Dist: onnx (==1.13.0)
Requires-Dist: onnxruntime (==1.13.1)
Requires-Dist: pydantic (==1.10.4)
Requires-Dist: tomlkit (==0.11.6)
